LICENSE.txt
MANIFEST.in
README.rst
setup.cfg
setup.py
djqgrid/__init__.py
djqgrid/columns.py
djqgrid/grid.py
djqgrid/grid_registrar.py
djqgrid/json_helpers.py
djqgrid/urls.py
djqgrid/views.py
djqgrid.egg-info/PKG-INFO
djqgrid.egg-info/SOURCES.txt
djqgrid.egg-info/dependency_links.txt
djqgrid.egg-info/requires.txt
djqgrid.egg-info/top_level.txt
djqgrid/static/js/djqgrid_utils.js
djqgrid/templatetags/__init__.py
djqgrid/templatetags/jqgrid.py
docs/.DS_Store
docs/.project
docs/Makefile
docs/conf.py
docs/example.rst
docs/index.rst
docs/installation.rst
docs/make.bat
docs/_build/doctrees/environment.pickle
docs/_build/doctrees/example.doctree
docs/_build/doctrees/index.doctree
docs/_build/doctrees/installation.doctree
docs/_build/doctrees/reference/columns.doctree
docs/_build/doctrees/reference/grid.doctree
docs/_build/doctrees/reference/index.doctree
docs/_build/doctrees/reference/templatetag.doctree
docs/_build/doctrees/reference/utilities.doctree
docs/_build/html/.buildinfo
docs/_build/html/example.html
docs/_build/html/genindex.html
docs/_build/html/index.html
docs/_build/html/installation.html
docs/_build/html/objects.inv
docs/_build/html/py-modindex.html
docs/_build/html/search.html
docs/_build/html/searchindex.js
docs/_build/html/_sources/example.txt
docs/_build/html/_sources/index.txt
docs/_build/html/_sources/installation.txt
docs/_build/html/_sources/reference/columns.txt
docs/_build/html/_sources/reference/grid.txt
docs/_build/html/_sources/reference/index.txt
docs/_build/html/_sources/reference/templatetag.txt
docs/_build/html/_sources/reference/utilities.txt
docs/_build/html/_static/ajax-loader.gif
docs/_build/html/_static/basic.css
docs/_build/html/_static/comment-bright.png
docs/_build/html/_static/comment-close.png
docs/_build/html/_static/comment.png
docs/_build/html/_static/default.css
docs/_build/html/_static/doctools.js
docs/_build/html/_static/down-pressed.png
docs/_build/html/_static/down.png
docs/_build/html/_static/file.png
docs/_build/html/_static/jquery.js
docs/_build/html/_static/minus.png
docs/_build/html/_static/plus.png
docs/_build/html/_static/pygments.css
