Metadata-Version: 1.1
Name: djqgrid
Version: 0.2
Summary: A Django wrapper for jqGrid
Home-page: https://github.com/zmbq/djqgrid/
Author: Itay Zandbank
Author-email: zmbq@platonix.com
License: MIT license
Keywords: django jqgrid client-side grid
Platform: UNKNOWN
Classifier: Environment :: Web Environment
Classifier: Framework :: Django
Classifier: Intended Audience :: Developers
Classifier: License :: OSI Approved :: MIT License
Classifier: Operating System :: OS Independent
Classifier: Programming Language :: Python
Classifier: Programming Language :: Python :: 2
Classifier: Programming Language :: Python :: 2.7
Classifier: Programming Language :: Python :: 3
Classifier: Programming Language :: Python :: 3.3
Classifier: Topic :: Internet :: WWW/HTTP
Classifier: Topic :: Internet :: WWW/HTTP :: Dynamic Content
Classifier: Development Status :: 3 - Alpha
